MANIFEST.in
README.rst
setup.py
confirmed_email/__init__.py
confirmed_email/manage.py
confirmed_email/models.py
confirmed_email/sender.py
confirmed_email/settings_test.py
confirmed_email/urls.py
confirmed_email/views.py
confirmed_email/templates/address_confirmed.html
confirmed_email/templates/confirmation_email.txt
confirmed_email/templates/confirmation_required.html
django_confirmed_email.egg-info/PKG-INFO
django_confirmed_email.egg-info/SOURCES.txt
django_confirmed_email.egg-info/dependency_links.txt
django_confirmed_email.egg-info/top_level.txt