Metadata-Version: 1.1
Name: django-confirmed-email
Version: 0.0.7
Summary: Provides an email sender that automatically confirms addresses.
Home-page: https://github.com/JivanAmara/confirmed-email
Author: Jivan Amara
Author-email: Development@JivanAmara.net
License: UNKNOWN
Platform: UNKNOWN
Classifier: Programming Language :: Python :: 2.7
Classifier: Programming Language :: Python :: 3.4
Classifier: Framework :: Django :: 1.5
Classifier: Framework :: Django :: 1.6
Classifier: Framework :: Django :: 1.7
Classifier: Framework :: Django :: 1.8
Classifier: Framework :: Django :: 1.9
Classifier: License :: OSI Approved :: MIT License
